{
  "name": "alloy-smelting",
  "title": "Alloy Smelting",
  "description": "Kilns for recipes that need hotter ore more specific temperatures.",
  "author": "SafTheLamb",
  "version": "0.3.1",
  "factorio_version": "2.0",
  "homepage": "https://github.com/SafTheLamb/fm-alloy-smelting",
  "package": {
    "ignore": ["thumbnail.afphoto", "**/*.afphoto", "**/*.ase", "**/*.afphoto~lock~", "**/*.pdn"]
  },
  "dependencies": [
    "base >= 2.0.32",
    "fdsl >= 0.1.8",
    "? space-age",
    "? crushing-industry >= 0.1.8",
    "? bztin",
    "? bzlead",
    "? bztitanium",
    "? hot-metals",
    "(?) Glass",
    "(?) aai-industry"
  ]
}
